{"name":"Add a post","id":"add-buzz-post;add-a-post","scenarioId":"classpath:features/AddBuzzPost:Add a post","methodName":"Add a post","testSteps":[{"number":1,"description":"Given user is on home page","duration":7912,"startTime":"2025-01-04T01:20:23.552162600+05:30[Asia/Colombo]","screenshots":[{"screenshot":"09275e093dc38fd3e7c95c66d6580a90b18c1f96bdfc9ecb4766b707a38d2a1b.png","timeStamp":1735933831471,"screenshotName":"09275e093dc38fd3e7c95c66d6580a90b18c1f96bdfc9ecb4766b707a38d2a1b.png"}],"result":"SUCCESS","precondition":false,"level":0,"children":[{"number":2,"description":"Opening Page","duration":7367,"startTime":"2025-01-04T01:20:24.097122500+05:30[Asia/Colombo]","screenshots":[{"screenshot":"09275e093dc38fd3e7c95c66d6580a90b18c1f96bdfc9ecb4766b707a38d2a1b.png","timeStamp":1735933831463,"screenshotName":"09275e093dc38fd3e7c95c66d6580a90b18c1f96bdfc9ecb4766b707a38d2a1b.png"}],"result":"SUCCESS","precondition":false,"level":1}]},{"number":3,"description":"When user enters \"Admin\" as username","duration":267,"startTime":"2025-01-04T01:20:31.474095100+05:30[Asia/Colombo]","screenshots":[{"screenshot":"4aaa4be37287d18c1bcc3dcf7d0d934df9c80e7c5430289386abe1ddb28be2ff.png","timeStamp":1735933831748,"screenshotName":"4aaa4be37287d18c1bcc3dcf7d0d934df9c80e7c5430289386abe1ddb28be2ff.png"}],"result":"SUCCESS","precondition":false,"level":0,"children":[{"number":4,"description":"Entering username as Admin","duration":264,"startTime":"2025-01-04T01:20:31.476089800+05:30[Asia/Colombo]","screenshots":[{"screenshot":"4aaa4be37287d18c1bcc3dcf7d0d934df9c80e7c5430289386abe1ddb28be2ff.png","timeStamp":1735933831740,"screenshotName":"4aaa4be37287d18c1bcc3dcf7d0d934df9c80e7c5430289386abe1ddb28be2ff.png"}],"result":"SUCCESS","precondition":false,"level":1}]},{"number":5,"description":"And user enters \"admin123\" as password","duration":2020,"startTime":"2025-01-04T01:20:31.748365500+05:30[Asia/Colombo]","screenshots":[{"screenshot":"d8d97b9014aa991a626cf0edc4d1c19dfe4a420f5be88f759ca3f7a6498c407a.png","timeStamp":1735933833774,"screenshotName":"d8d97b9014aa991a626cf0edc4d1c19dfe4a420f5be88f759ca3f7a6498c407a.png"}],"result":"SUCCESS","precondition":false,"level":0,"children":[{"number":6,"description":"Entering password as admin123","duration":240,"startTime":"2025-01-04T01:20:31.751352800+05:30[Asia/Colombo]","screenshots":[{"screenshot":"7077a91a1da0064d7aa763eedfad4b0588c0cc51c6033cd8d888895c8b191609.png","timeStamp":1735933831991,"screenshotName":"7077a91a1da0064d7aa763eedfad4b0588c0cc51c6033cd8d888895c8b191609.png"}],"result":"SUCCESS","precondition":false,"level":1},{"number":7,"description":"Clicking Login Button","duration":1775,"startTime":"2025-01-04T01:20:31.992708100+05:30[Asia/Colombo]","screenshots":[{"screenshot":"d8d97b9014aa991a626cf0edc4d1c19dfe4a420f5be88f759ca3f7a6498c407a.png","timeStamp":1735933833768,"screenshotName":"d8d97b9014aa991a626cf0edc4d1c19dfe4a420f5be88f759ca3f7a6498c407a.png"}],"result":"SUCCESS","precondition":false,"level":1}]},{"number":8,"description":"Then user should be on dashboard page","duration":30,"startTime":"2025-01-04T01:20:33.774525500+05:30[Asia/Colombo]","screenshots":[{"screenshot":"d8d97b9014aa991a626cf0edc4d1c19dfe4a420f5be88f759ca3f7a6498c407a.png","timeStamp":1735933833813,"screenshotName":"d8d97b9014aa991a626cf0edc4d1c19dfe4a420f5be88f759ca3f7a6498c407a.png"}],"result":"SUCCESS","precondition":false,"level":0,"children":[{"number":9,"description":"verify is on dashboard page","duration":23,"startTime":"2025-01-04T01:20:33.781507200+05:30[Asia/Colombo]","screenshots":[{"screenshot":"d8d97b9014aa991a626cf0edc4d1c19dfe4a420f5be88f759ca3f7a6498c407a.png","timeStamp":1735933833805,"screenshotName":"d8d97b9014aa991a626cf0edc4d1c19dfe4a420f5be88f759ca3f7a6498c407a.png"}],"result":"SUCCESS","precondition":false,"level":1}]},{"number":10,"description":"Given user is on buzz page","duration":935,"startTime":"2025-01-04T01:20:33.813421100+05:30[Asia/Colombo]","screenshots":[{"screenshot":"d8d97b9014aa991a626cf0edc4d1c19dfe4a420f5be88f759ca3f7a6498c407a.png","timeStamp":1735933834753,"screenshotName":"d8d97b9014aa991a626cf0edc4d1c19dfe4a420f5be88f759ca3f7a6498c407a.png"}],"result":"SUCCESS","precondition":false,"level":0,"children":[{"number":11,"description":"Open buzz page","duration":860,"startTime":"2025-01-04T01:20:33.888221900+05:30[Asia/Colombo]","screenshots":[{"screenshot":"d8d97b9014aa991a626cf0edc4d1c19dfe4a420f5be88f759ca3f7a6498c407a.png","timeStamp":1735933834748,"screenshotName":"d8d97b9014aa991a626cf0edc4d1c19dfe4a420f5be88f759ca3f7a6498c407a.png"}],"result":"SUCCESS","precondition":false,"level":1}]},{"number":12,"description":"When user types \"this is a new post for testing on 8191227\" on post input field","duration":2345,"startTime":"2025-01-04T01:20:34.753905700+05:30[Asia/Colombo]","screenshots":[{"screenshot":"e299c441ccad9aff653d8102242d5a8342ba13749d318b4a9ea348b8e0fd85fc.png","timeStamp":1735933837103,"screenshotName":"e299c441ccad9aff653d8102242d5a8342ba13749d318b4a9ea348b8e0fd85fc.png"}],"result":"SUCCESS","precondition":false,"level":0,"children":[{"number":13,"description":"Type into post: this is a new post for testing on 8191227","duration":337,"startTime":"2025-01-04T01:20:36.761722300+05:30[Asia/Colombo]","screenshots":[{"screenshot":"e299c441ccad9aff653d8102242d5a8342ba13749d318b4a9ea348b8e0fd85fc.png","timeStamp":1735933837098,"screenshotName":"e299c441ccad9aff653d8102242d5a8342ba13749d318b4a9ea348b8e0fd85fc.png"}],"result":"SUCCESS","precondition":false,"level":1}]},{"number":14,"description":"And user clicks on the post button","duration":3384,"startTime":"2025-01-04T01:20:37.104802800+05:30[Asia/Colombo]","screenshots":[{"screenshot":"f11c42b67f729c12bc5581bcbfb55c21f18a8122da36a7ea2cd500bc67e11b10.png","timeStamp":1735933840495,"screenshotName":"f11c42b67f729c12bc5581bcbfb55c21f18a8122da36a7ea2cd500bc67e11b10.png"}],"result":"SUCCESS","precondition":false,"level":0,"children":[{"number":15,"description":"Click post button","duration":373,"startTime":"2025-01-04T01:20:40.113952100+05:30[Asia/Colombo]","screenshots":[{"screenshot":"f11c42b67f729c12bc5581bcbfb55c21f18a8122da36a7ea2cd500bc67e11b10.png","timeStamp":1735933840487,"screenshotName":"f11c42b67f729c12bc5581bcbfb55c21f18a8122da36a7ea2cd500bc67e11b10.png"}],"result":"SUCCESS","precondition":false,"level":1}]},{"number":16,"description":"Then user can see the post with content \"this is a new post for testing on 8191227\"","duration":174,"startTime":"2025-01-04T01:20:40.495925200+05:30[Asia/Colombo]","screenshots":[{"screenshot":"ef03262f21f4d7d9bd7f4cd056a2ef3f84eb1beaebc9482c4dda9f3d3ed625ef.png","timeStamp":1735933840682,"screenshotName":"ef03262f21f4d7d9bd7f4cd056a2ef3f84eb1beaebc9482c4dda9f3d3ed625ef.png"}],"result":"SUCCESS","precondition":false,"level":0,"children":[{"number":17,"description":"Verify post available: this is a new post for testing on 8191227","duration":172,"startTime":"2025-01-04T01:20:40.497919200+05:30[Asia/Colombo]","screenshots":[{"screenshot":"ef03262f21f4d7d9bd7f4cd056a2ef3f84eb1beaebc9482c4dda9f3d3ed625ef.png","timeStamp":1735933840670,"screenshotName":"ef03262f21f4d7d9bd7f4cd056a2ef3f84eb1beaebc9482c4dda9f3d3ed625ef.png"}],"result":"SUCCESS","precondition":false,"level":1}]}],"userStory":{"id":"classpath:features/AddBuzzPost","storyName":"Add Buzz Post","displayName":"Add Buzz Post","path":"AddBuzzPost","pathElements":[{"name":"AddBuzzPost","description":""}],"type":"feature"},"title":"Add a post","description":"","backgroundTitle":"","backgroundDescription":"","tags":[{"name":"Chrome","type":"context","displayName":"Chrome"},{"name":"Windows","type":"context","displayName":"Windows"},{"name":"Chrome, Windows","type":"context","displayName":"Chrome, Windows"}],"startTime":"2025-01-04T01:20:15.892755600+05:30[Asia/Colombo]","endTime":"2025-01-04T01:20:41.112610700+05:30[Asia/Colombo]","duration":25219,"projectKey":"","isManualTestingUpToDate":false,"context":"chrome,windows","manual":false,"testSource":"Cucumber","result":"SUCCESS"}