{"name":"Add expenses and submit","id":"submit-a-claim;add-expenses-and-submit","scenarioId":"classpath:features/SubmitClaim:Add expenses and submit","methodName":"Add expenses and submit","testSteps":[{"number":1,"description":"1: Add expenses and submit ({ExpenseType\u003dPlanned Surgery, Amount\u003d100, Date\u003d2025-02-01, Note\u003dMeal})","duration":32452,"startTime":"2025-01-04T01:33:49.296742200+05:30[Asia/Colombo]","result":"SUCCESS","precondition":false,"level":0,"lineNumber":33,"children":[{"number":2,"description":"Given user is logged in as an Admin","duration":3980,"startTime":"2025-01-04T01:33:52.381533300+05:30[Asia/Colombo]","screenshots":[{"screenshot":"d8d97b9014aa991a626cf0edc4d1c19dfe4a420f5be88f759ca3f7a6498c407a.png","timeStamp":1735934638021,"screenshotName":"d8d97b9014aa991a626cf0edc4d1c19dfe4a420f5be88f759ca3f7a6498c407a.png"}],"result":"SUCCESS","precondition":false,"level":1},{"number":3,"description":"Given the user is on the Claims Page","duration":757,"startTime":"2025-01-04T01:33:58.021298700+05:30[Asia/Colombo]","screenshots":[{"screenshot":"d8d97b9014aa991a626cf0edc4d1c19dfe4a420f5be88f759ca3f7a6498c407a.png","timeStamp":1735934638781,"screenshotName":"d8d97b9014aa991a626cf0edc4d1c19dfe4a420f5be88f759ca3f7a6498c407a.png"}],"result":"SUCCESS","precondition":false,"level":1,"children":[{"number":4,"description":"Open claims page","duration":727,"startTime":"2025-01-04T01:33:58.051222500+05:30[Asia/Colombo]","screenshots":[{"screenshot":"d8d97b9014aa991a626cf0edc4d1c19dfe4a420f5be88f759ca3f7a6498c407a.png","timeStamp":1735934638778,"screenshotName":"d8d97b9014aa991a626cf0edc4d1c19dfe4a420f5be88f759ca3f7a6498c407a.png"}],"result":"SUCCESS","precondition":false,"level":2}]},{"number":5,"description":"When the user clicks the Submit Claim button","duration":1994,"startTime":"2025-01-04T01:33:58.781749400+05:30[Asia/Colombo]","screenshots":[{"screenshot":"d8d97b9014aa991a626cf0edc4d1c19dfe4a420f5be88f759ca3f7a6498c407a.png","timeStamp":1735934640780,"screenshotName":"d8d97b9014aa991a626cf0edc4d1c19dfe4a420f5be88f759ca3f7a6498c407a.png"}],"result":"SUCCESS","precondition":false,"level":1,"children":[{"number":6,"description":"Click submit claim button","duration":1994,"startTime":"2025-01-04T01:33:58.781749400+05:30[Asia/Colombo]","screenshots":[{"screenshot":"d8d97b9014aa991a626cf0edc4d1c19dfe4a420f5be88f759ca3f7a6498c407a.png","timeStamp":1735934640775,"screenshotName":"d8d97b9014aa991a626cf0edc4d1c19dfe4a420f5be88f759ca3f7a6498c407a.png"}],"result":"SUCCESS","precondition":false,"level":2}]},{"number":7,"description":"And the user is navigated to the Submit Claim page","duration":13,"startTime":"2025-01-04T01:34:00.781736+05:30[Asia/Colombo]","screenshots":[{"screenshot":"d8d97b9014aa991a626cf0edc4d1c19dfe4a420f5be88f759ca3f7a6498c407a.png","timeStamp":1735934640801,"screenshotName":"d8d97b9014aa991a626cf0edc4d1c19dfe4a420f5be88f759ca3f7a6498c407a.png"}],"result":"SUCCESS","precondition":false,"level":1,"children":[{"number":8,"description":"Verify submit claim page","duration":13,"startTime":"2025-01-04T01:34:00.781736+05:30[Asia/Colombo]","screenshots":[{"screenshot":"d8d97b9014aa991a626cf0edc4d1c19dfe4a420f5be88f759ca3f7a6498c407a.png","timeStamp":1735934640795,"screenshotName":"d8d97b9014aa991a626cf0edc4d1c19dfe4a420f5be88f759ca3f7a6498c407a.png"}],"result":"SUCCESS","precondition":false,"level":2}]},{"number":9,"description":"And the user selects the Event \"Medical Reimbursement\"","duration":845,"startTime":"2025-01-04T01:34:00.801682500+05:30[Asia/Colombo]","screenshots":[{"screenshot":"5d2ed530c96f0795e30c02223627e3608966926fd6a3e50d254c73e542d5f59c.png","timeStamp":1735934641651,"screenshotName":"5d2ed530c96f0795e30c02223627e3608966926fd6a3e50d254c73e542d5f59c.png"}],"result":"SUCCESS","precondition":false,"level":1,"children":[{"number":10,"description":"Select event: Medical Reimbursement","duration":843,"startTime":"2025-01-04T01:34:00.802680100+05:30[Asia/Colombo]","screenshots":[{"screenshot":"5d2ed530c96f0795e30c02223627e3608966926fd6a3e50d254c73e542d5f59c.png","timeStamp":1735934641646,"screenshotName":"5d2ed530c96f0795e30c02223627e3608966926fd6a3e50d254c73e542d5f59c.png"}],"result":"SUCCESS","precondition":false,"level":2}]},{"number":11,"description":"And the user selects the Currency \"United States Dollar\"","duration":387,"startTime":"2025-01-04T01:34:01.652568300+05:30[Asia/Colombo]","screenshots":[{"screenshot":"289cab333defd3dd7844bbe32b6bd57712221aee259ba9c01b25f4c951652370.png","timeStamp":1735934642045,"screenshotName":"289cab333defd3dd7844bbe32b6bd57712221aee259ba9c01b25f4c951652370.png"}],"result":"SUCCESS","precondition":false,"level":1,"children":[{"number":12,"description":"Select currency: United States Dollar","duration":387,"startTime":"2025-01-04T01:34:01.652568300+05:30[Asia/Colombo]","screenshots":[{"screenshot":"289cab333defd3dd7844bbe32b6bd57712221aee259ba9c01b25f4c951652370.png","timeStamp":1735934642040,"screenshotName":"289cab333defd3dd7844bbe32b6bd57712221aee259ba9c01b25f4c951652370.png"}],"result":"SUCCESS","precondition":false,"level":2}]},{"number":13,"description":"And the user enters Remarks \"Hospital Stay\"","duration":197,"startTime":"2025-01-04T01:34:02.045540400+05:30[Asia/Colombo]","screenshots":[{"screenshot":"635f2211d22b62fe8cca2fc29657aa3769ab9bd7ba41e368d83a77a21b9261ab.png","timeStamp":1735934642251,"screenshotName":"635f2211d22b62fe8cca2fc29657aa3769ab9bd7ba41e368d83a77a21b9261ab.png"}],"result":"SUCCESS","precondition":false,"level":1,"children":[{"number":14,"description":"Enter remarks: Hospital Stay","duration":196,"startTime":"2025-01-04T01:34:02.046538100+05:30[Asia/Colombo]","screenshots":[{"screenshot":"635f2211d22b62fe8cca2fc29657aa3769ab9bd7ba41e368d83a77a21b9261ab.png","timeStamp":1735934642243,"screenshotName":"635f2211d22b62fe8cca2fc29657aa3769ab9bd7ba41e368d83a77a21b9261ab.png"}],"result":"SUCCESS","precondition":false,"level":2}]},{"number":15,"description":"And the user clicks the Create button","duration":5292,"startTime":"2025-01-04T01:34:02.251987900+05:30[Asia/Colombo]","screenshots":[{"screenshot":"dc0ecc9da8a28928e34c35bb864dcc51ec6699bc63367b89d0f55ff19b3e66d9.png","timeStamp":1735934647548,"screenshotName":"dc0ecc9da8a28928e34c35bb864dcc51ec6699bc63367b89d0f55ff19b3e66d9.png"}],"result":"SUCCESS","precondition":false,"level":1,"children":[{"number":16,"description":"Click create button","duration":5292,"startTime":"2025-01-04T01:34:02.251987900+05:30[Asia/Colombo]","screenshots":[{"screenshot":"dc0ecc9da8a28928e34c35bb864dcc51ec6699bc63367b89d0f55ff19b3e66d9.png","timeStamp":1735934647544,"screenshotName":"dc0ecc9da8a28928e34c35bb864dcc51ec6699bc63367b89d0f55ff19b3e66d9.png"}],"result":"SUCCESS","precondition":false,"level":2}]},{"number":17,"description":"Then the user is directed to the View Claim page","duration":36,"startTime":"2025-01-04T01:34:07.548804700+05:30[Asia/Colombo]","screenshots":[{"screenshot":"dc0ecc9da8a28928e34c35bb864dcc51ec6699bc63367b89d0f55ff19b3e66d9.png","timeStamp":1735934647590,"screenshotName":"dc0ecc9da8a28928e34c35bb864dcc51ec6699bc63367b89d0f55ff19b3e66d9.png"}],"result":"SUCCESS","precondition":false,"level":1,"children":[{"number":18,"description":"Verify navigate to view claim page","duration":35,"startTime":"2025-01-04T01:34:07.549797400+05:30[Asia/Colombo]","screenshots":[{"screenshot":"dc0ecc9da8a28928e34c35bb864dcc51ec6699bc63367b89d0f55ff19b3e66d9.png","timeStamp":1735934647585,"screenshotName":"dc0ecc9da8a28928e34c35bb864dcc51ec6699bc63367b89d0f55ff19b3e66d9.png"}],"result":"SUCCESS","precondition":false,"level":2}]},{"number":19,"description":"And the user should see the claim details Event \"Medical Reimbursement\" and Currency \"United States Dollar\" and Remarks \"Hospital Stay\"","duration":157,"startTime":"2025-01-04T01:34:07.590687+05:30[Asia/Colombo]","screenshots":[{"screenshot":"dc0ecc9da8a28928e34c35bb864dcc51ec6699bc63367b89d0f55ff19b3e66d9.png","timeStamp":1735934647750,"screenshotName":"dc0ecc9da8a28928e34c35bb864dcc51ec6699bc63367b89d0f55ff19b3e66d9.png"}],"result":"SUCCESS","precondition":false,"level":1,"children":[{"number":20,"description":"Verify claim details: Medical Reimbursement, United States Dollar, Hospital Stay","duration":156,"startTime":"2025-01-04T01:34:07.591684500+05:30[Asia/Colombo]","screenshots":[{"screenshot":"dc0ecc9da8a28928e34c35bb864dcc51ec6699bc63367b89d0f55ff19b3e66d9.png","timeStamp":1735934647747,"screenshotName":"dc0ecc9da8a28928e34c35bb864dcc51ec6699bc63367b89d0f55ff19b3e66d9.png"}],"result":"SUCCESS","precondition":false,"level":2}]},{"number":21,"description":"Given the user is directed to the View Claim page","duration":41,"startTime":"2025-01-04T01:34:07.750259700+05:30[Asia/Colombo]","screenshots":[{"screenshot":"dc0ecc9da8a28928e34c35bb864dcc51ec6699bc63367b89d0f55ff19b3e66d9.png","timeStamp":1735934647796,"screenshotName":"dc0ecc9da8a28928e34c35bb864dcc51ec6699bc63367b89d0f55ff19b3e66d9.png"}],"result":"SUCCESS","precondition":false,"level":1,"children":[{"number":22,"description":"Verify navigate to view claim page","duration":40,"startTime":"2025-01-04T01:34:07.751259200+05:30[Asia/Colombo]","screenshots":[{"screenshot":"dc0ecc9da8a28928e34c35bb864dcc51ec6699bc63367b89d0f55ff19b3e66d9.png","timeStamp":1735934647792,"screenshotName":"dc0ecc9da8a28928e34c35bb864dcc51ec6699bc63367b89d0f55ff19b3e66d9.png"}],"result":"SUCCESS","precondition":false,"level":2}]},{"number":23,"description":"When the user clicks the Add Expenses button","duration":319,"startTime":"2025-01-04T01:34:07.797133700+05:30[Asia/Colombo]","screenshots":[{"screenshot":"927b49ccfd12ae308a6271fc66344d2d44f240b8280d8a2a03b6e60cfb21a36c.png","timeStamp":1735934648122,"screenshotName":"927b49ccfd12ae308a6271fc66344d2d44f240b8280d8a2a03b6e60cfb21a36c.png"}],"result":"SUCCESS","precondition":false,"level":1,"children":[{"number":24,"description":"Click add button","duration":289,"startTime":"2025-01-04T01:34:07.827054600+05:30[Asia/Colombo]","screenshots":[{"screenshot":"927b49ccfd12ae308a6271fc66344d2d44f240b8280d8a2a03b6e60cfb21a36c.png","timeStamp":1735934648116,"screenshotName":"927b49ccfd12ae308a6271fc66344d2d44f240b8280d8a2a03b6e60cfb21a36c.png"}],"result":"SUCCESS","precondition":false,"level":2}]},{"number":25,"description":"Then the add expenses modal should be displayed","duration":42,"startTime":"2025-01-04T01:34:08.122265200+05:30[Asia/Colombo]","screenshots":[{"screenshot":"acf98ca7af8dcfd8e9898775c4cc8fd2e88eda803e42d9ee91aa54937b7722b1.png","timeStamp":1735934648277,"screenshotName":"acf98ca7af8dcfd8e9898775c4cc8fd2e88eda803e42d9ee91aa54937b7722b1.png"}],"result":"SUCCESS","precondition":false,"level":1,"children":[{"number":26,"description":"Verify add expense modal","duration":41,"startTime":"2025-01-04T01:34:08.123262500+05:30[Asia/Colombo]","screenshots":[{"screenshot":"927b49ccfd12ae308a6271fc66344d2d44f240b8280d8a2a03b6e60cfb21a36c.png","timeStamp":1735934648165,"screenshotName":"927b49ccfd12ae308a6271fc66344d2d44f240b8280d8a2a03b6e60cfb21a36c.png"}],"result":"SUCCESS","precondition":false,"level":2}]},{"number":27,"description":"And the user selects the Expense Type \"Planned Surgery\"","duration":364,"startTime":"2025-01-04T01:34:08.277848700+05:30[Asia/Colombo]","screenshots":[{"screenshot":"079ab4e03a859ec80a02cdbfb86516ab04147a5c900b00465d658baae5ef60e9.png","timeStamp":1735934648646,"screenshotName":"079ab4e03a859ec80a02cdbfb86516ab04147a5c900b00465d658baae5ef60e9.png"}],"result":"SUCCESS","precondition":false,"level":1,"children":[{"number":28,"description":"Select expense type: Planned Surgery","duration":363,"startTime":"2025-01-04T01:34:08.278846900+05:30[Asia/Colombo]","screenshots":[{"screenshot":"079ab4e03a859ec80a02cdbfb86516ab04147a5c900b00465d658baae5ef60e9.png","timeStamp":1735934648641,"screenshotName":"079ab4e03a859ec80a02cdbfb86516ab04147a5c900b00465d658baae5ef60e9.png"}],"result":"SUCCESS","precondition":false,"level":2}]},{"number":29,"description":"And the user enters the Amount \"100\"","duration":268,"startTime":"2025-01-04T01:34:08.646861300+05:30[Asia/Colombo]","screenshots":[{"screenshot":"965fb9fede3728add1879299da237ae02b6d41fe763e3847d1e31058f6a68b17.png","timeStamp":1735934648918,"screenshotName":"965fb9fede3728add1879299da237ae02b6d41fe763e3847d1e31058f6a68b17.png"}],"result":"SUCCESS","precondition":false,"level":1,"children":[{"number":30,"description":"Enter expense amount: 100","duration":267,"startTime":"2025-01-04T01:34:08.647859400+05:30[Asia/Colombo]","screenshots":[{"screenshot":"965fb9fede3728add1879299da237ae02b6d41fe763e3847d1e31058f6a68b17.png","timeStamp":1735934648915,"screenshotName":"965fb9fede3728add1879299da237ae02b6d41fe763e3847d1e31058f6a68b17.png"}],"result":"SUCCESS","precondition":false,"level":2}]},{"number":31,"description":"And the user enters the Date \"2025-02-01\"","duration":183,"startTime":"2025-01-04T01:34:08.918139600+05:30[Asia/Colombo]","screenshots":[{"screenshot":"3db0e2c324cd358a071764b23f9e11318907e3d454b65514921ba2b2a06d9fdd.png","timeStamp":1735934649104,"screenshotName":"3db0e2c324cd358a071764b23f9e11318907e3d454b65514921ba2b2a06d9fdd.png"}],"result":"SUCCESS","precondition":false,"level":1,"children":[{"number":32,"description":"Enter expense date: 2025-02-01","duration":183,"startTime":"2025-01-04T01:34:08.918139600+05:30[Asia/Colombo]","screenshots":[{"screenshot":"3db0e2c324cd358a071764b23f9e11318907e3d454b65514921ba2b2a06d9fdd.png","timeStamp":1735934649101,"screenshotName":"3db0e2c324cd358a071764b23f9e11318907e3d454b65514921ba2b2a06d9fdd.png"}],"result":"SUCCESS","precondition":false,"level":2}]},{"number":33,"description":"And the user enters the Note \"Meal\"","duration":170,"startTime":"2025-01-04T01:34:09.104248500+05:30[Asia/Colombo]","screenshots":[{"screenshot":"9ade615bb78fb86a1f11cb48ad6f97d195bdc71dce861f82174db30301965dcd.png","timeStamp":1735934649280,"screenshotName":"9ade615bb78fb86a1f11cb48ad6f97d195bdc71dce861f82174db30301965dcd.png"}],"result":"SUCCESS","precondition":false,"level":1,"children":[{"number":34,"description":"Enter expense note: Meal","duration":167,"startTime":"2025-01-04T01:34:09.105249+05:30[Asia/Colombo]","screenshots":[{"screenshot":"9ade615bb78fb86a1f11cb48ad6f97d195bdc71dce861f82174db30301965dcd.png","timeStamp":1735934649272,"screenshotName":"9ade615bb78fb86a1f11cb48ad6f97d195bdc71dce861f82174db30301965dcd.png"}],"result":"SUCCESS","precondition":false,"level":2}]},{"number":35,"description":"And the user clicks the save button","duration":3255,"startTime":"2025-01-04T01:34:09.280744500+05:30[Asia/Colombo]","screenshots":[{"screenshot":"2aa5ec470f04793be01f078ef066bdce8e615aad9a22ad804cef83a291e2098e.png","timeStamp":1735934652540,"screenshotName":"2aa5ec470f04793be01f078ef066bdce8e615aad9a22ad804cef83a291e2098e.png"}],"result":"SUCCESS","precondition":false,"level":1,"children":[{"number":36,"description":"Click save button","duration":3254,"startTime":"2025-01-04T01:34:09.281741700+05:30[Asia/Colombo]","screenshots":[{"screenshot":"2aa5ec470f04793be01f078ef066bdce8e615aad9a22ad804cef83a291e2098e.png","timeStamp":1735934652535,"screenshotName":"2aa5ec470f04793be01f078ef066bdce8e615aad9a22ad804cef83a291e2098e.png"}],"result":"SUCCESS","precondition":false,"level":2}]},{"number":37,"description":"Then the user should see the expense details Expense Type \"Planned Surgery\" and Amount \"100\" and Date \"2025-02-01\" and Note \"Meal\"","duration":260,"startTime":"2025-01-04T01:34:12.540584900+05:30[Asia/Colombo]","screenshots":[{"screenshot":"aa98728263acd175e1839d48ae9065f47a1856e6ad6894c21660cbe8e39574ec.png","timeStamp":1735934652804,"screenshotName":"aa98728263acd175e1839d48ae9065f47a1856e6ad6894c21660cbe8e39574ec.png"}],"result":"SUCCESS","precondition":false,"level":1,"children":[{"number":38,"description":"Verify expense details: Planned Surgery, 100, 2025-02-01, Meal","duration":258,"startTime":"2025-01-04T01:34:12.542577200+05:30[Asia/Colombo]","screenshots":[{"screenshot":"aa98728263acd175e1839d48ae9065f47a1856e6ad6894c21660cbe8e39574ec.png","timeStamp":1735934652801,"screenshotName":"aa98728263acd175e1839d48ae9065f47a1856e6ad6894c21660cbe8e39574ec.png"}],"result":"SUCCESS","precondition":false,"level":2}]},{"number":39,"description":"When the user clicks the Submit button","duration":3654,"startTime":"2025-01-04T01:34:12.805198300+05:30[Asia/Colombo]","screenshots":[{"screenshot":"d8d97b9014aa991a626cf0edc4d1c19dfe4a420f5be88f759ca3f7a6498c407a.png","timeStamp":1735934656461,"screenshotName":"d8d97b9014aa991a626cf0edc4d1c19dfe4a420f5be88f759ca3f7a6498c407a.png"}],"result":"SUCCESS","precondition":false,"level":1,"children":[{"number":40,"description":"Click submit button","duration":3654,"startTime":"2025-01-04T01:34:12.805198300+05:30[Asia/Colombo]","screenshots":[{"screenshot":"d8d97b9014aa991a626cf0edc4d1c19dfe4a420f5be88f759ca3f7a6498c407a.png","timeStamp":1735934656459,"screenshotName":"d8d97b9014aa991a626cf0edc4d1c19dfe4a420f5be88f759ca3f7a6498c407a.png"}],"result":"SUCCESS","precondition":false,"level":2}]},{"number":41,"description":"Then the user should see the claim status as \"Submitted\"","duration":5102,"startTime":"2025-01-04T01:34:16.461957400+05:30[Asia/Colombo]","screenshots":[{"screenshot":"5a41e6b7fa5a49ccb84732fcad6dfe490027eaf4e98d1549ef172fcdd7eb73d9.png","timeStamp":1735934661567,"screenshotName":"5a41e6b7fa5a49ccb84732fcad6dfe490027eaf4e98d1549ef172fcdd7eb73d9.png"}],"result":"SUCCESS","precondition":false,"level":1,"children":[{"number":42,"description":"Verify claim status: Submitted","duration":5102,"startTime":"2025-01-04T01:34:16.461957400+05:30[Asia/Colombo]","screenshots":[{"screenshot":"5a41e6b7fa5a49ccb84732fcad6dfe490027eaf4e98d1549ef172fcdd7eb73d9.png","timeStamp":1735934661564,"screenshotName":"5a41e6b7fa5a49ccb84732fcad6dfe490027eaf4e98d1549ef172fcdd7eb73d9.png"}],"result":"SUCCESS","precondition":false,"level":2}]}]},{"number":43,"description":"2: Add expenses and submit ({ExpenseType\u003dTransport, Amount\u003d200, Date\u003d2024-01-02, Note\u003dTaxi})","duration":32318,"startTime":"2025-01-04T01:34:21.760251+05:30[Asia/Colombo]","result":"SUCCESS","precondition":false,"level":0,"lineNumber":34,"children":[{"number":44,"description":"Given user is logged in as an Admin","duration":4259,"startTime":"2025-01-04T01:34:24.814354700+05:30[Asia/Colombo]","screenshots":[{"screenshot":"d8d97b9014aa991a626cf0edc4d1c19dfe4a420f5be88f759ca3f7a6498c407a.png","timeStamp":1735934670778,"screenshotName":"d8d97b9014aa991a626cf0edc4d1c19dfe4a420f5be88f759ca3f7a6498c407a.png"}],"result":"SUCCESS","precondition":false,"level":1},{"number":45,"description":"Given the user is on the Claims Page","duration":863,"startTime":"2025-01-04T01:34:30.778771400+05:30[Asia/Colombo]","screenshots":[{"screenshot":"d8d97b9014aa991a626cf0edc4d1c19dfe4a420f5be88f759ca3f7a6498c407a.png","timeStamp":1735934671648,"screenshotName":"d8d97b9014aa991a626cf0edc4d1c19dfe4a420f5be88f759ca3f7a6498c407a.png"}],"result":"SUCCESS","precondition":false,"level":1,"children":[{"number":46,"description":"Open claims page","duration":826,"startTime":"2025-01-04T01:34:30.815669900+05:30[Asia/Colombo]","screenshots":[{"screenshot":"d8d97b9014aa991a626cf0edc4d1c19dfe4a420f5be88f759ca3f7a6498c407a.png","timeStamp":1735934671642,"screenshotName":"d8d97b9014aa991a626cf0edc4d1c19dfe4a420f5be88f759ca3f7a6498c407a.png"}],"result":"SUCCESS","precondition":false,"level":2}]},{"number":47,"description":"When the user clicks the Submit Claim button","duration":1759,"startTime":"2025-01-04T01:34:31.648074600+05:30[Asia/Colombo]","screenshots":[{"screenshot":"d8d97b9014aa991a626cf0edc4d1c19dfe4a420f5be88f759ca3f7a6498c407a.png","timeStamp":1735934673414,"screenshotName":"d8d97b9014aa991a626cf0edc4d1c19dfe4a420f5be88f759ca3f7a6498c407a.png"}],"result":"SUCCESS","precondition":false,"level":1,"children":[{"number":48,"description":"Click submit claim button","duration":1758,"startTime":"2025-01-04T01:34:31.649072300+05:30[Asia/Colombo]","screenshots":[{"screenshot":"d8d97b9014aa991a626cf0edc4d1c19dfe4a420f5be88f759ca3f7a6498c407a.png","timeStamp":1735934673408,"screenshotName":"d8d97b9014aa991a626cf0edc4d1c19dfe4a420f5be88f759ca3f7a6498c407a.png"}],"result":"SUCCESS","precondition":false,"level":2}]},{"number":49,"description":"And the user is navigated to the Submit Claim page","duration":11,"startTime":"2025-01-04T01:34:33.414007500+05:30[Asia/Colombo]","screenshots":[{"screenshot":"d8d97b9014aa991a626cf0edc4d1c19dfe4a420f5be88f759ca3f7a6498c407a.png","timeStamp":1735934673430,"screenshotName":"d8d97b9014aa991a626cf0edc4d1c19dfe4a420f5be88f759ca3f7a6498c407a.png"}],"result":"SUCCESS","precondition":false,"level":1,"children":[{"number":50,"description":"Verify submit claim page","duration":11,"startTime":"2025-01-04T01:34:33.414007500+05:30[Asia/Colombo]","screenshots":[{"screenshot":"d8d97b9014aa991a626cf0edc4d1c19dfe4a420f5be88f759ca3f7a6498c407a.png","timeStamp":1735934673426,"screenshotName":"d8d97b9014aa991a626cf0edc4d1c19dfe4a420f5be88f759ca3f7a6498c407a.png"}],"result":"SUCCESS","precondition":false,"level":2}]},{"number":51,"description":"And the user selects the Event \"Medical Reimbursement\"","duration":824,"startTime":"2025-01-04T01:34:33.431016900+05:30[Asia/Colombo]","screenshots":[{"screenshot":"5d2ed530c96f0795e30c02223627e3608966926fd6a3e50d254c73e542d5f59c.png","timeStamp":1735934674258,"screenshotName":"5d2ed530c96f0795e30c02223627e3608966926fd6a3e50d254c73e542d5f59c.png"}],"result":"SUCCESS","precondition":false,"level":1,"children":[{"number":52,"description":"Select event: Medical Reimbursement","duration":824,"startTime":"2025-01-04T01:34:33.431016900+05:30[Asia/Colombo]","screenshots":[{"screenshot":"5d2ed530c96f0795e30c02223627e3608966926fd6a3e50d254c73e542d5f59c.png","timeStamp":1735934674255,"screenshotName":"5d2ed530c96f0795e30c02223627e3608966926fd6a3e50d254c73e542d5f59c.png"}],"result":"SUCCESS","precondition":false,"level":2}]},{"number":53,"description":"And the user selects the Currency \"United States Dollar\"","duration":335,"startTime":"2025-01-04T01:34:34.258783+05:30[Asia/Colombo]","screenshots":[{"screenshot":"289cab333defd3dd7844bbe32b6bd57712221aee259ba9c01b25f4c951652370.png","timeStamp":1735934674598,"screenshotName":"289cab333defd3dd7844bbe32b6bd57712221aee259ba9c01b25f4c951652370.png"}],"result":"SUCCESS","precondition":false,"level":1,"children":[{"number":54,"description":"Select currency: United States Dollar","duration":335,"startTime":"2025-01-04T01:34:34.258783+05:30[Asia/Colombo]","screenshots":[{"screenshot":"289cab333defd3dd7844bbe32b6bd57712221aee259ba9c01b25f4c951652370.png","timeStamp":1735934674594,"screenshotName":"289cab333defd3dd7844bbe32b6bd57712221aee259ba9c01b25f4c951652370.png"}],"result":"SUCCESS","precondition":false,"level":2}]},{"number":55,"description":"And the user enters Remarks \"Hospital Stay\"","duration":181,"startTime":"2025-01-04T01:34:34.598471900+05:30[Asia/Colombo]","screenshots":[{"screenshot":"635f2211d22b62fe8cca2fc29657aa3769ab9bd7ba41e368d83a77a21b9261ab.png","timeStamp":1735934674785,"screenshotName":"635f2211d22b62fe8cca2fc29657aa3769ab9bd7ba41e368d83a77a21b9261ab.png"}],"result":"SUCCESS","precondition":false,"level":1,"children":[{"number":56,"description":"Enter remarks: Hospital Stay","duration":180,"startTime":"2025-01-04T01:34:34.599469500+05:30[Asia/Colombo]","screenshots":[{"screenshot":"635f2211d22b62fe8cca2fc29657aa3769ab9bd7ba41e368d83a77a21b9261ab.png","timeStamp":1735934674779,"screenshotName":"635f2211d22b62fe8cca2fc29657aa3769ab9bd7ba41e368d83a77a21b9261ab.png"}],"result":"SUCCESS","precondition":false,"level":2}]},{"number":57,"description":"And the user clicks the Create button","duration":5287,"startTime":"2025-01-04T01:34:34.785971200+05:30[Asia/Colombo]","screenshots":[{"screenshot":"7a6fd17abf502e4194d1b05637edcd520ad21d86f8946fb00abcc7a63ea42732.png","timeStamp":1735934680075,"screenshotName":"7a6fd17abf502e4194d1b05637edcd520ad21d86f8946fb00abcc7a63ea42732.png"}],"result":"SUCCESS","precondition":false,"level":1,"children":[{"number":58,"description":"Click create button","duration":5285,"startTime":"2025-01-04T01:34:34.787966300+05:30[Asia/Colombo]","screenshots":[{"screenshot":"7a6fd17abf502e4194d1b05637edcd520ad21d86f8946fb00abcc7a63ea42732.png","timeStamp":1735934680073,"screenshotName":"7a6fd17abf502e4194d1b05637edcd520ad21d86f8946fb00abcc7a63ea42732.png"}],"result":"SUCCESS","precondition":false,"level":2}]},{"number":59,"description":"Then the user is directed to the View Claim page","duration":30,"startTime":"2025-01-04T01:34:40.075906600+05:30[Asia/Colombo]","screenshots":[{"screenshot":"7a6fd17abf502e4194d1b05637edcd520ad21d86f8946fb00abcc7a63ea42732.png","timeStamp":1735934680108,"screenshotName":"7a6fd17abf502e4194d1b05637edcd520ad21d86f8946fb00abcc7a63ea42732.png"}],"result":"SUCCESS","precondition":false,"level":1,"children":[{"number":60,"description":"Verify navigate to view claim page","duration":29,"startTime":"2025-01-04T01:34:40.076872+05:30[Asia/Colombo]","screenshots":[{"screenshot":"7a6fd17abf502e4194d1b05637edcd520ad21d86f8946fb00abcc7a63ea42732.png","timeStamp":1735934680106,"screenshotName":"7a6fd17abf502e4194d1b05637edcd520ad21d86f8946fb00abcc7a63ea42732.png"}],"result":"SUCCESS","precondition":false,"level":2}]},{"number":61,"description":"And the user should see the claim details Event \"Medical Reimbursement\" and Currency \"United States Dollar\" and Remarks \"Hospital Stay\"","duration":124,"startTime":"2025-01-04T01:34:40.108818500+05:30[Asia/Colombo]","screenshots":[{"screenshot":"7a6fd17abf502e4194d1b05637edcd520ad21d86f8946fb00abcc7a63ea42732.png","timeStamp":1735934680238,"screenshotName":"7a6fd17abf502e4194d1b05637edcd520ad21d86f8946fb00abcc7a63ea42732.png"}],"result":"SUCCESS","precondition":false,"level":1,"children":[{"number":62,"description":"Verify claim details: Medical Reimbursement, United States Dollar, Hospital Stay","duration":124,"startTime":"2025-01-04T01:34:40.108818500+05:30[Asia/Colombo]","screenshots":[{"screenshot":"7a6fd17abf502e4194d1b05637edcd520ad21d86f8946fb00abcc7a63ea42732.png","timeStamp":1735934680233,"screenshotName":"7a6fd17abf502e4194d1b05637edcd520ad21d86f8946fb00abcc7a63ea42732.png"}],"result":"SUCCESS","precondition":false,"level":2}]},{"number":63,"description":"Given the user is directed to the View Claim page","duration":34,"startTime":"2025-01-04T01:34:40.238488300+05:30[Asia/Colombo]","screenshots":[{"screenshot":"7a6fd17abf502e4194d1b05637edcd520ad21d86f8946fb00abcc7a63ea42732.png","timeStamp":1735934680276,"screenshotName":"7a6fd17abf502e4194d1b05637edcd520ad21d86f8946fb00abcc7a63ea42732.png"}],"result":"SUCCESS","precondition":false,"level":1,"children":[{"number":64,"description":"Verify navigate to view claim page","duration":33,"startTime":"2025-01-04T01:34:40.239484900+05:30[Asia/Colombo]","screenshots":[{"screenshot":"7a6fd17abf502e4194d1b05637edcd520ad21d86f8946fb00abcc7a63ea42732.png","timeStamp":1735934680273,"screenshotName":"7a6fd17abf502e4194d1b05637edcd520ad21d86f8946fb00abcc7a63ea42732.png"}],"result":"SUCCESS","precondition":false,"level":2}]},{"number":65,"description":"When the user clicks the Add Expenses button","duration":241,"startTime":"2025-01-04T01:34:40.276464100+05:30[Asia/Colombo]","screenshots":[{"screenshot":"6b2b029fa1a1763c82e51475ec91b8b4f07195521fc084c1f5db1bea061489e6.png","timeStamp":1735934680522,"screenshotName":"6b2b029fa1a1763c82e51475ec91b8b4f07195521fc084c1f5db1bea061489e6.png"}],"result":"SUCCESS","precondition":false,"level":1,"children":[{"number":66,"description":"Click add button","duration":229,"startTime":"2025-01-04T01:34:40.287437700+05:30[Asia/Colombo]","screenshots":[{"screenshot":"6b2b029fa1a1763c82e51475ec91b8b4f07195521fc084c1f5db1bea061489e6.png","timeStamp":1735934680517,"screenshotName":"6b2b029fa1a1763c82e51475ec91b8b4f07195521fc084c1f5db1bea061489e6.png"}],"result":"SUCCESS","precondition":false,"level":2}]},{"number":67,"description":"Then the add expenses modal should be displayed","duration":29,"startTime":"2025-01-04T01:34:40.522309100+05:30[Asia/Colombo]","screenshots":[{"screenshot":"6b2b029fa1a1763c82e51475ec91b8b4f07195521fc084c1f5db1bea061489e6.png","timeStamp":1735934680555,"screenshotName":"6b2b029fa1a1763c82e51475ec91b8b4f07195521fc084c1f5db1bea061489e6.png"}],"result":"SUCCESS","precondition":false,"level":1,"children":[{"number":68,"description":"Verify add expense modal","duration":28,"startTime":"2025-01-04T01:34:40.523307600+05:30[Asia/Colombo]","screenshots":[{"screenshot":"6b2b029fa1a1763c82e51475ec91b8b4f07195521fc084c1f5db1bea061489e6.png","timeStamp":1735934680552,"screenshotName":"6b2b029fa1a1763c82e51475ec91b8b4f07195521fc084c1f5db1bea061489e6.png"}],"result":"SUCCESS","precondition":false,"level":2}]},{"number":69,"description":"And the user selects the Expense Type \"Transport\"","duration":443,"startTime":"2025-01-04T01:34:40.556218400+05:30[Asia/Colombo]","screenshots":[{"screenshot":"877bfd67bfe677e6730d5160a3911689e465958364f826bf24b458d7d1fd8688.png","timeStamp":1735934681003,"screenshotName":"877bfd67bfe677e6730d5160a3911689e465958364f826bf24b458d7d1fd8688.png"}],"result":"SUCCESS","precondition":false,"level":1,"children":[{"number":70,"description":"Select expense type: Transport","duration":442,"startTime":"2025-01-04T01:34:40.556218400+05:30[Asia/Colombo]","screenshots":[{"screenshot":"877bfd67bfe677e6730d5160a3911689e465958364f826bf24b458d7d1fd8688.png","timeStamp":1735934680998,"screenshotName":"877bfd67bfe677e6730d5160a3911689e465958364f826bf24b458d7d1fd8688.png"}],"result":"SUCCESS","precondition":false,"level":2}]},{"number":71,"description":"And the user enters the Amount \"200\"","duration":182,"startTime":"2025-01-04T01:34:41.003886200+05:30[Asia/Colombo]","screenshots":[{"screenshot":"e8be5a8819f54fbf9516c778fd2764d3344c05f0849cd3befd5a1bc9944af736.png","timeStamp":1735934681191,"screenshotName":"e8be5a8819f54fbf9516c778fd2764d3344c05f0849cd3befd5a1bc9944af736.png"}],"result":"SUCCESS","precondition":false,"level":1,"children":[{"number":72,"description":"Enter expense amount: 200","duration":182,"startTime":"2025-01-04T01:34:41.003886200+05:30[Asia/Colombo]","screenshots":[{"screenshot":"e8be5a8819f54fbf9516c778fd2764d3344c05f0849cd3befd5a1bc9944af736.png","timeStamp":1735934681186,"screenshotName":"e8be5a8819f54fbf9516c778fd2764d3344c05f0849cd3befd5a1bc9944af736.png"}],"result":"SUCCESS","precondition":false,"level":2}]},{"number":73,"description":"And the user enters the Date \"2024-01-02\"","duration":184,"startTime":"2025-01-04T01:34:41.191384700+05:30[Asia/Colombo]","screenshots":[{"screenshot":"fb7b2fcb58ffaf3e84df2ce4f9b84efb43a63332b1c7e3f03bc8f2c84d266a9c.png","timeStamp":1735934681378,"screenshotName":"fb7b2fcb58ffaf3e84df2ce4f9b84efb43a63332b1c7e3f03bc8f2c84d266a9c.png"}],"result":"SUCCESS","precondition":false,"level":1,"children":[{"number":74,"description":"Enter expense date: 2024-01-02","duration":184,"startTime":"2025-01-04T01:34:41.191384700+05:30[Asia/Colombo]","screenshots":[{"screenshot":"fb7b2fcb58ffaf3e84df2ce4f9b84efb43a63332b1c7e3f03bc8f2c84d266a9c.png","timeStamp":1735934681375,"screenshotName":"fb7b2fcb58ffaf3e84df2ce4f9b84efb43a63332b1c7e3f03bc8f2c84d266a9c.png"}],"result":"SUCCESS","precondition":false,"level":2}]},{"number":75,"description":"And the user enters the Note \"Taxi\"","duration":167,"startTime":"2025-01-04T01:34:41.378882900+05:30[Asia/Colombo]","screenshots":[{"screenshot":"aed798b3ef08b31d2a4f9200b6f5878b4aa5174595dd39b713002b0c7e0e8fe1.png","timeStamp":1735934681549,"screenshotName":"aed798b3ef08b31d2a4f9200b6f5878b4aa5174595dd39b713002b0c7e0e8fe1.png"}],"result":"SUCCESS","precondition":false,"level":1,"children":[{"number":76,"description":"Enter expense note: Taxi","duration":166,"startTime":"2025-01-04T01:34:41.379880800+05:30[Asia/Colombo]","screenshots":[{"screenshot":"aed798b3ef08b31d2a4f9200b6f5878b4aa5174595dd39b713002b0c7e0e8fe1.png","timeStamp":1735934681546,"screenshotName":"aed798b3ef08b31d2a4f9200b6f5878b4aa5174595dd39b713002b0c7e0e8fe1.png"}],"result":"SUCCESS","precondition":false,"level":2}]},{"number":77,"description":"And the user clicks the save button","duration":3202,"startTime":"2025-01-04T01:34:41.549426500+05:30[Asia/Colombo]","screenshots":[{"screenshot":"559f9472f3e21ade4e0fd5ffb245601165357d0c3051735691e42264015c1c41.png","timeStamp":1735934684753,"screenshotName":"559f9472f3e21ade4e0fd5ffb245601165357d0c3051735691e42264015c1c41.png"}],"result":"SUCCESS","precondition":false,"level":1,"children":[{"number":78,"description":"Click save button","duration":3200,"startTime":"2025-01-04T01:34:41.551422100+05:30[Asia/Colombo]","screenshots":[{"screenshot":"559f9472f3e21ade4e0fd5ffb245601165357d0c3051735691e42264015c1c41.png","timeStamp":1735934684751,"screenshotName":"559f9472f3e21ade4e0fd5ffb245601165357d0c3051735691e42264015c1c41.png"}],"result":"SUCCESS","precondition":false,"level":2}]},{"number":79,"description":"Then the user should see the expense details Expense Type \"Transport\" and Amount \"200\" and Date \"2024-01-02\" and Note \"Taxi\"","duration":247,"startTime":"2025-01-04T01:34:44.753817100+05:30[Asia/Colombo]","screenshots":[{"screenshot":"794758a663a5d790ce339254ce71f277611e436dd8ada8e7a8d685484de1ba05.png","timeStamp":1735934685004,"screenshotName":"794758a663a5d790ce339254ce71f277611e436dd8ada8e7a8d685484de1ba05.png"}],"result":"SUCCESS","precondition":false,"level":1,"children":[{"number":80,"description":"Verify expense details: Transport, 200, 2024-01-02, Taxi","duration":246,"startTime":"2025-01-04T01:34:44.754813100+05:30[Asia/Colombo]","screenshots":[{"screenshot":"794758a663a5d790ce339254ce71f277611e436dd8ada8e7a8d685484de1ba05.png","timeStamp":1735934685001,"screenshotName":"794758a663a5d790ce339254ce71f277611e436dd8ada8e7a8d685484de1ba05.png"}],"result":"SUCCESS","precondition":false,"level":2}]},{"number":81,"description":"When the user clicks the Submit button","duration":3726,"startTime":"2025-01-04T01:34:45.004571+05:30[Asia/Colombo]","screenshots":[{"screenshot":"d8d97b9014aa991a626cf0edc4d1c19dfe4a420f5be88f759ca3f7a6498c407a.png","timeStamp":1735934688735,"screenshotName":"d8d97b9014aa991a626cf0edc4d1c19dfe4a420f5be88f759ca3f7a6498c407a.png"}],"result":"SUCCESS","precondition":false,"level":1,"children":[{"number":82,"description":"Click submit button","duration":3726,"startTime":"2025-01-04T01:34:45.004571+05:30[Asia/Colombo]","screenshots":[{"screenshot":"d8d97b9014aa991a626cf0edc4d1c19dfe4a420f5be88f759ca3f7a6498c407a.png","timeStamp":1735934688730,"screenshotName":"d8d97b9014aa991a626cf0edc4d1c19dfe4a420f5be88f759ca3f7a6498c407a.png"}],"result":"SUCCESS","precondition":false,"level":2}]},{"number":83,"description":"Then the user should see the claim status as \"Submitted\"","duration":5093,"startTime":"2025-01-04T01:34:48.736671+05:30[Asia/Colombo]","screenshots":[{"screenshot":"e3941175a80dcf9362ad93d82c8d0d00f41b158ae271883c3a8034bcea983b45.png","timeStamp":1735934693832,"screenshotName":"e3941175a80dcf9362ad93d82c8d0d00f41b158ae271883c3a8034bcea983b45.png"}],"result":"SUCCESS","precondition":false,"level":1,"children":[{"number":84,"description":"Verify claim status: Submitted","duration":5093,"startTime":"2025-01-04T01:34:48.736671+05:30[Asia/Colombo]","screenshots":[{"screenshot":"e3941175a80dcf9362ad93d82c8d0d00f41b158ae271883c3a8034bcea983b45.png","timeStamp":1735934693829,"screenshotName":"e3941175a80dcf9362ad93d82c8d0d00f41b158ae271883c3a8034bcea983b45.png"}],"result":"SUCCESS","precondition":false,"level":2}]}]},{"number":85,"description":"3: Add expenses and submit ({ExpenseType\u003dAccommodation, Amount\u003d300, Date\u003d2023-12-03, Note\u003dHotel})","duration":33978,"startTime":"2025-01-04T01:34:54.089507100+05:30[Asia/Colombo]","result":"SUCCESS","precondition":false,"level":0,"lineNumber":35,"children":[{"number":86,"description":"Given user is logged in as an Admin","duration":4486,"startTime":"2025-01-04T01:34:57.070670700+05:30[Asia/Colombo]","screenshots":[{"screenshot":"d8d97b9014aa991a626cf0edc4d1c19dfe4a420f5be88f759ca3f7a6498c407a.png","timeStamp":1735934703463,"screenshotName":"d8d97b9014aa991a626cf0edc4d1c19dfe4a420f5be88f759ca3f7a6498c407a.png"}],"result":"SUCCESS","precondition":false,"level":1},{"number":87,"description":"Given the user is on the Claims Page","duration":972,"startTime":"2025-01-04T01:35:03.463077700+05:30[Asia/Colombo]","screenshots":[{"screenshot":"d8d97b9014aa991a626cf0edc4d1c19dfe4a420f5be88f759ca3f7a6498c407a.png","timeStamp":1735934704439,"screenshotName":"d8d97b9014aa991a626cf0edc4d1c19dfe4a420f5be88f759ca3f7a6498c407a.png"}],"result":"SUCCESS","precondition":false,"level":1,"children":[{"number":88,"description":"Open claims page","duration":873,"startTime":"2025-01-04T01:35:03.561815400+05:30[Asia/Colombo]","screenshots":[{"screenshot":"d8d97b9014aa991a626cf0edc4d1c19dfe4a420f5be88f759ca3f7a6498c407a.png","timeStamp":1735934704435,"screenshotName":"d8d97b9014aa991a626cf0edc4d1c19dfe4a420f5be88f759ca3f7a6498c407a.png"}],"result":"SUCCESS","precondition":false,"level":2}]},{"number":89,"description":"When the user clicks the Submit Claim button","duration":2321,"startTime":"2025-01-04T01:35:04.440590300+05:30[Asia/Colombo]","screenshots":[{"screenshot":"d8d97b9014aa991a626cf0edc4d1c19dfe4a420f5be88f759ca3f7a6498c407a.png","timeStamp":1735934706767,"screenshotName":"d8d97b9014aa991a626cf0edc4d1c19dfe4a420f5be88f759ca3f7a6498c407a.png"}],"result":"SUCCESS","precondition":false,"level":1,"children":[{"number":90,"description":"Click submit claim button","duration":2321,"startTime":"2025-01-04T01:35:04.440590300+05:30[Asia/Colombo]","screenshots":[{"screenshot":"d8d97b9014aa991a626cf0edc4d1c19dfe4a420f5be88f759ca3f7a6498c407a.png","timeStamp":1735934706762,"screenshotName":"d8d97b9014aa991a626cf0edc4d1c19dfe4a420f5be88f759ca3f7a6498c407a.png"}],"result":"SUCCESS","precondition":false,"level":2}]},{"number":91,"description":"And the user is navigated to the Submit Claim page","duration":7,"startTime":"2025-01-04T01:35:06.767495600+05:30[Asia/Colombo]","screenshots":[{"screenshot":"d8d97b9014aa991a626cf0edc4d1c19dfe4a420f5be88f759ca3f7a6498c407a.png","timeStamp":1735934706777,"screenshotName":"d8d97b9014aa991a626cf0edc4d1c19dfe4a420f5be88f759ca3f7a6498c407a.png"}],"result":"SUCCESS","precondition":false,"level":1,"children":[{"number":92,"description":"Verify submit claim page","duration":6,"startTime":"2025-01-04T01:35:06.768495500+05:30[Asia/Colombo]","screenshots":[{"screenshot":"d8d97b9014aa991a626cf0edc4d1c19dfe4a420f5be88f759ca3f7a6498c407a.png","timeStamp":1735934706775,"screenshotName":"d8d97b9014aa991a626cf0edc4d1c19dfe4a420f5be88f759ca3f7a6498c407a.png"}],"result":"SUCCESS","precondition":false,"level":2}]},{"number":93,"description":"And the user selects the Event \"Medical Reimbursement\"","duration":995,"startTime":"2025-01-04T01:35:06.777469600+05:30[Asia/Colombo]","screenshots":[{"screenshot":"7b7c4c80f93feb2126521192a6632c5adf3b3778d83d5f665b740c594fb30317.png","timeStamp":1735934707777,"screenshotName":"7b7c4c80f93feb2126521192a6632c5adf3b3778d83d5f665b740c594fb30317.png"}],"result":"SUCCESS","precondition":false,"level":1,"children":[{"number":94,"description":"Select event: Medical Reimbursement","duration":995,"startTime":"2025-01-04T01:35:06.777469600+05:30[Asia/Colombo]","screenshots":[{"screenshot":"7b7c4c80f93feb2126521192a6632c5adf3b3778d83d5f665b740c594fb30317.png","timeStamp":1735934707772,"screenshotName":"7b7c4c80f93feb2126521192a6632c5adf3b3778d83d5f665b740c594fb30317.png"}],"result":"SUCCESS","precondition":false,"level":2}]},{"number":95,"description":"And the user selects the Currency \"United States Dollar\"","duration":406,"startTime":"2025-01-04T01:35:07.778793800+05:30[Asia/Colombo]","screenshots":[{"screenshot":"b7c0b428f377cfd4e76dfc95f44d213b0981e1cb2fe47681bde336e29f9cabdc.png","timeStamp":1735934708189,"screenshotName":"b7c0b428f377cfd4e76dfc95f44d213b0981e1cb2fe47681bde336e29f9cabdc.png"}],"result":"SUCCESS","precondition":false,"level":1,"children":[{"number":96,"description":"Select currency: United States Dollar","duration":406,"startTime":"2025-01-04T01:35:07.778793800+05:30[Asia/Colombo]","screenshots":[{"screenshot":"b7c0b428f377cfd4e76dfc95f44d213b0981e1cb2fe47681bde336e29f9cabdc.png","timeStamp":1735934708185,"screenshotName":"b7c0b428f377cfd4e76dfc95f44d213b0981e1cb2fe47681bde336e29f9cabdc.png"}],"result":"SUCCESS","precondition":false,"level":2}]},{"number":97,"description":"And the user enters Remarks \"Hospital Stay\"","duration":184,"startTime":"2025-01-04T01:35:08.190205300+05:30[Asia/Colombo]","screenshots":[{"screenshot":"70a9fe8adda0fec783c8755616ca05490e17eb5ef3b250fe4601817c94cb31b2.png","timeStamp":1735934708378,"screenshotName":"70a9fe8adda0fec783c8755616ca05490e17eb5ef3b250fe4601817c94cb31b2.png"}],"result":"SUCCESS","precondition":false,"level":1,"children":[{"number":98,"description":"Enter remarks: Hospital Stay","duration":183,"startTime":"2025-01-04T01:35:08.190205300+05:30[Asia/Colombo]","screenshots":[{"screenshot":"70a9fe8adda0fec783c8755616ca05490e17eb5ef3b250fe4601817c94cb31b2.png","timeStamp":1735934708373,"screenshotName":"70a9fe8adda0fec783c8755616ca05490e17eb5ef3b250fe4601817c94cb31b2.png"}],"result":"SUCCESS","precondition":false,"level":2}]},{"number":99,"description":"And the user clicks the Create button","duration":5330,"startTime":"2025-01-04T01:35:08.378216+05:30[Asia/Colombo]","screenshots":[{"screenshot":"f48c2bbeeaeda935c231e5f6e0290e95838e8fbe3fe222e174af03225470bfc0.png","timeStamp":1735934713711,"screenshotName":"f48c2bbeeaeda935c231e5f6e0290e95838e8fbe3fe222e174af03225470bfc0.png"}],"result":"SUCCESS","precondition":false,"level":1,"children":[{"number":100,"description":"Click create button","duration":5330,"startTime":"2025-01-04T01:35:08.378216+05:30[Asia/Colombo]","screenshots":[{"screenshot":"f48c2bbeeaeda935c231e5f6e0290e95838e8fbe3fe222e174af03225470bfc0.png","timeStamp":1735934713708,"screenshotName":"f48c2bbeeaeda935c231e5f6e0290e95838e8fbe3fe222e174af03225470bfc0.png"}],"result":"SUCCESS","precondition":false,"level":2}]},{"number":101,"description":"Then the user is directed to the View Claim page","duration":43,"startTime":"2025-01-04T01:35:13.711832500+05:30[Asia/Colombo]","screenshots":[{"screenshot":"f48c2bbeeaeda935c231e5f6e0290e95838e8fbe3fe222e174af03225470bfc0.png","timeStamp":1735934713757,"screenshotName":"f48c2bbeeaeda935c231e5f6e0290e95838e8fbe3fe222e174af03225470bfc0.png"}],"result":"SUCCESS","precondition":false,"level":1,"children":[{"number":102,"description":"Verify navigate to view claim page","duration":43,"startTime":"2025-01-04T01:35:13.711832500+05:30[Asia/Colombo]","screenshots":[{"screenshot":"f48c2bbeeaeda935c231e5f6e0290e95838e8fbe3fe222e174af03225470bfc0.png","timeStamp":1735934713755,"screenshotName":"f48c2bbeeaeda935c231e5f6e0290e95838e8fbe3fe222e174af03225470bfc0.png"}],"result":"SUCCESS","precondition":false,"level":2}]},{"number":103,"description":"And the user should see the claim details Event \"Medical Reimbursement\" and Currency \"United States Dollar\" and Remarks \"Hospital Stay\"","duration":128,"startTime":"2025-01-04T01:35:13.758709+05:30[Asia/Colombo]","screenshots":[{"screenshot":"f48c2bbeeaeda935c231e5f6e0290e95838e8fbe3fe222e174af03225470bfc0.png","timeStamp":1735934713889,"screenshotName":"f48c2bbeeaeda935c231e5f6e0290e95838e8fbe3fe222e174af03225470bfc0.png"}],"result":"SUCCESS","precondition":false,"level":1,"children":[{"number":104,"description":"Verify claim details: Medical Reimbursement, United States Dollar, Hospital Stay","duration":128,"startTime":"2025-01-04T01:35:13.758709+05:30[Asia/Colombo]","screenshots":[{"screenshot":"f48c2bbeeaeda935c231e5f6e0290e95838e8fbe3fe222e174af03225470bfc0.png","timeStamp":1735934713886,"screenshotName":"f48c2bbeeaeda935c231e5f6e0290e95838e8fbe3fe222e174af03225470bfc0.png"}],"result":"SUCCESS","precondition":false,"level":2}]},{"number":105,"description":"Given the user is directed to the View Claim page","duration":27,"startTime":"2025-01-04T01:35:13.889789100+05:30[Asia/Colombo]","screenshots":[{"screenshot":"f48c2bbeeaeda935c231e5f6e0290e95838e8fbe3fe222e174af03225470bfc0.png","timeStamp":1735934713921,"screenshotName":"f48c2bbeeaeda935c231e5f6e0290e95838e8fbe3fe222e174af03225470bfc0.png"}],"result":"SUCCESS","precondition":false,"level":1,"children":[{"number":106,"description":"Verify navigate to view claim page","duration":27,"startTime":"2025-01-04T01:35:13.889789100+05:30[Asia/Colombo]","screenshots":[{"screenshot":"f48c2bbeeaeda935c231e5f6e0290e95838e8fbe3fe222e174af03225470bfc0.png","timeStamp":1735934713917,"screenshotName":"f48c2bbeeaeda935c231e5f6e0290e95838e8fbe3fe222e174af03225470bfc0.png"}],"result":"SUCCESS","precondition":false,"level":2}]},{"number":107,"description":"When the user clicks the Add Expenses button","duration":231,"startTime":"2025-01-04T01:35:13.921215800+05:30[Asia/Colombo]","screenshots":[{"screenshot":"bea2e6139e167826a9e8d94fc7ca7f19937a5c8f12965a915cbfda57172e18f0.png","timeStamp":1735934714154,"screenshotName":"bea2e6139e167826a9e8d94fc7ca7f19937a5c8f12965a915cbfda57172e18f0.png"}],"result":"SUCCESS","precondition":false,"level":1,"children":[{"number":108,"description":"Click add button","duration":218,"startTime":"2025-01-04T01:35:13.934182900+05:30[Asia/Colombo]","screenshots":[{"screenshot":"bea2e6139e167826a9e8d94fc7ca7f19937a5c8f12965a915cbfda57172e18f0.png","timeStamp":1735934714152,"screenshotName":"bea2e6139e167826a9e8d94fc7ca7f19937a5c8f12965a915cbfda57172e18f0.png"}],"result":"SUCCESS","precondition":false,"level":2}]},{"number":109,"description":"Then the add expenses modal should be displayed","duration":32,"startTime":"2025-01-04T01:35:14.154614800+05:30[Asia/Colombo]","screenshots":[{"screenshot":"bea2e6139e167826a9e8d94fc7ca7f19937a5c8f12965a915cbfda57172e18f0.png","timeStamp":1735934714190,"screenshotName":"bea2e6139e167826a9e8d94fc7ca7f19937a5c8f12965a915cbfda57172e18f0.png"}],"result":"SUCCESS","precondition":false,"level":1,"children":[{"number":110,"description":"Verify add expense modal","duration":31,"startTime":"2025-01-04T01:35:14.155611800+05:30[Asia/Colombo]","screenshots":[{"screenshot":"bea2e6139e167826a9e8d94fc7ca7f19937a5c8f12965a915cbfda57172e18f0.png","timeStamp":1735934714187,"screenshotName":"bea2e6139e167826a9e8d94fc7ca7f19937a5c8f12965a915cbfda57172e18f0.png"}],"result":"SUCCESS","precondition":false,"level":2}]},{"number":111,"description":"And the user selects the Expense Type \"Accommodation\"","duration":496,"startTime":"2025-01-04T01:35:14.190518200+05:30[Asia/Colombo]","screenshots":[{"screenshot":"cdccbd38d8d00719977e108782926272b5fb664e4ea4e5b8a536902645a2a4d7.png","timeStamp":1735934714690,"screenshotName":"cdccbd38d8d00719977e108782926272b5fb664e4ea4e5b8a536902645a2a4d7.png"}],"result":"SUCCESS","precondition":false,"level":1,"children":[{"number":112,"description":"Select expense type: Accommodation","duration":496,"startTime":"2025-01-04T01:35:14.190518200+05:30[Asia/Colombo]","screenshots":[{"screenshot":"cdccbd38d8d00719977e108782926272b5fb664e4ea4e5b8a536902645a2a4d7.png","timeStamp":1735934714687,"screenshotName":"cdccbd38d8d00719977e108782926272b5fb664e4ea4e5b8a536902645a2a4d7.png"}],"result":"SUCCESS","precondition":false,"level":2}]},{"number":113,"description":"And the user enters the Amount \"300\"","duration":161,"startTime":"2025-01-04T01:35:14.690016900+05:30[Asia/Colombo]","screenshots":[{"screenshot":"241eaf6155d9b833d9b5a99411e05ba5a643551e47a4c73cdfc9c7948fb303d2.png","timeStamp":1735934714853,"screenshotName":"241eaf6155d9b833d9b5a99411e05ba5a643551e47a4c73cdfc9c7948fb303d2.png"}],"result":"SUCCESS","precondition":false,"level":1,"children":[{"number":114,"description":"Enter expense amount: 300","duration":161,"startTime":"2025-01-04T01:35:14.690016900+05:30[Asia/Colombo]","screenshots":[{"screenshot":"241eaf6155d9b833d9b5a99411e05ba5a643551e47a4c73cdfc9c7948fb303d2.png","timeStamp":1735934714851,"screenshotName":"241eaf6155d9b833d9b5a99411e05ba5a643551e47a4c73cdfc9c7948fb303d2.png"}],"result":"SUCCESS","precondition":false,"level":2}]},{"number":115,"description":"And the user enters the Date \"2023-12-03\"","duration":145,"startTime":"2025-01-04T01:35:14.854576200+05:30[Asia/Colombo]","screenshots":[{"screenshot":"e9738a85ebaed86c58d8ccadb5d6c1f5968bd0123c572f6da066a12af1a67ecc.png","timeStamp":1735934715003,"screenshotName":"e9738a85ebaed86c58d8ccadb5d6c1f5968bd0123c572f6da066a12af1a67ecc.png"}],"result":"SUCCESS","precondition":false,"level":1,"children":[{"number":116,"description":"Enter expense date: 2023-12-03","duration":145,"startTime":"2025-01-04T01:35:14.854576200+05:30[Asia/Colombo]","screenshots":[{"screenshot":"e9738a85ebaed86c58d8ccadb5d6c1f5968bd0123c572f6da066a12af1a67ecc.png","timeStamp":1735934715000,"screenshotName":"e9738a85ebaed86c58d8ccadb5d6c1f5968bd0123c572f6da066a12af1a67ecc.png"}],"result":"SUCCESS","precondition":false,"level":2}]},{"number":117,"description":"And the user enters the Note \"Hotel\"","duration":164,"startTime":"2025-01-04T01:35:15.003178800+05:30[Asia/Colombo]","screenshots":[{"screenshot":"407f72fe84e7f1e3f50725f4f827e1143f7f4a9c8385d697150c8bfd35deea32.png","timeStamp":1735934715170,"screenshotName":"407f72fe84e7f1e3f50725f4f827e1143f7f4a9c8385d697150c8bfd35deea32.png"}],"result":"SUCCESS","precondition":false,"level":1,"children":[{"number":118,"description":"Enter expense note: Hotel","duration":163,"startTime":"2025-01-04T01:35:15.004175400+05:30[Asia/Colombo]","screenshots":[{"screenshot":"407f72fe84e7f1e3f50725f4f827e1143f7f4a9c8385d697150c8bfd35deea32.png","timeStamp":1735934715167,"screenshotName":"407f72fe84e7f1e3f50725f4f827e1143f7f4a9c8385d697150c8bfd35deea32.png"}],"result":"SUCCESS","precondition":false,"level":2}]},{"number":119,"description":"And the user clicks the save button","duration":3194,"startTime":"2025-01-04T01:35:15.170817600+05:30[Asia/Colombo]","screenshots":[{"screenshot":"e2c49a0a65b417f07468f8f35ef1df0b7253e5dffbd91e068bdaf5c31652b430.png","timeStamp":1735934718368,"screenshotName":"e2c49a0a65b417f07468f8f35ef1df0b7253e5dffbd91e068bdaf5c31652b430.png"}],"result":"SUCCESS","precondition":false,"level":1,"children":[{"number":120,"description":"Click save button","duration":3194,"startTime":"2025-01-04T01:35:15.170817600+05:30[Asia/Colombo]","screenshots":[{"screenshot":"e2c49a0a65b417f07468f8f35ef1df0b7253e5dffbd91e068bdaf5c31652b430.png","timeStamp":1735934718365,"screenshotName":"e2c49a0a65b417f07468f8f35ef1df0b7253e5dffbd91e068bdaf5c31652b430.png"}],"result":"SUCCESS","precondition":false,"level":2}]},{"number":121,"description":"Then the user should see the expense details Expense Type \"Accommodation\" and Amount \"300\" and Date \"2023-12-03\" and Note \"Hotel\"","duration":395,"startTime":"2025-01-04T01:35:18.368449800+05:30[Asia/Colombo]","screenshots":[{"screenshot":"206cf4f9b5cb2b456d1b6d31b73e19bf570b49ebe3c41508c8a7d9ccba8acb02.png","timeStamp":1735934718767,"screenshotName":"206cf4f9b5cb2b456d1b6d31b73e19bf570b49ebe3c41508c8a7d9ccba8acb02.png"}],"result":"SUCCESS","precondition":false,"level":1,"children":[{"number":122,"description":"Verify expense details: Accommodation, 300, 2023-12-03, Hotel","duration":395,"startTime":"2025-01-04T01:35:18.368449800+05:30[Asia/Colombo]","screenshots":[{"screenshot":"206cf4f9b5cb2b456d1b6d31b73e19bf570b49ebe3c41508c8a7d9ccba8acb02.png","timeStamp":1735934718764,"screenshotName":"206cf4f9b5cb2b456d1b6d31b73e19bf570b49ebe3c41508c8a7d9ccba8acb02.png"}],"result":"SUCCESS","precondition":false,"level":2}]},{"number":123,"description":"When the user clicks the Submit button","duration":3735,"startTime":"2025-01-04T01:35:18.767299100+05:30[Asia/Colombo]","screenshots":[{"screenshot":"d8d97b9014aa991a626cf0edc4d1c19dfe4a420f5be88f759ca3f7a6498c407a.png","timeStamp":1735934722507,"screenshotName":"d8d97b9014aa991a626cf0edc4d1c19dfe4a420f5be88f759ca3f7a6498c407a.png"}],"result":"SUCCESS","precondition":false,"level":1,"children":[{"number":124,"description":"Click submit button","duration":3734,"startTime":"2025-01-04T01:35:18.768297900+05:30[Asia/Colombo]","screenshots":[{"screenshot":"d8d97b9014aa991a626cf0edc4d1c19dfe4a420f5be88f759ca3f7a6498c407a.png","timeStamp":1735934722502,"screenshotName":"d8d97b9014aa991a626cf0edc4d1c19dfe4a420f5be88f759ca3f7a6498c407a.png"}],"result":"SUCCESS","precondition":false,"level":2}]},{"number":125,"description":"Then the user should see the claim status as \"Submitted\"","duration":5089,"startTime":"2025-01-04T01:35:22.507657700+05:30[Asia/Colombo]","screenshots":[{"screenshot":"68c80950c73b25d6d4ef84e26155df8a9a62b1e31e9e3d1eb83063ccce29bbcf.png","timeStamp":1735934727600,"screenshotName":"68c80950c73b25d6d4ef84e26155df8a9a62b1e31e9e3d1eb83063ccce29bbcf.png"}],"result":"SUCCESS","precondition":false,"level":1,"children":[{"number":126,"description":"Verify claim status: Submitted","duration":5089,"startTime":"2025-01-04T01:35:22.507657700+05:30[Asia/Colombo]","screenshots":[{"screenshot":"68c80950c73b25d6d4ef84e26155df8a9a62b1e31e9e3d1eb83063ccce29bbcf.png","timeStamp":1735934727597,"screenshotName":"68c80950c73b25d6d4ef84e26155df8a9a62b1e31e9e3d1eb83063ccce29bbcf.png"}],"result":"SUCCESS","precondition":false,"level":2}]}]}],"userStory":{"id":"classpath:features/SubmitClaim","storyName":"Submit a Claim","displayName":"Submit a Claim","path":"SubmitClaim","pathElements":[{"name":"SubmitClaim","description":""}],"type":"feature"},"title":"Add expenses and submit","description":"","backgroundTitle":"","backgroundDescription":"","tags":[{"name":"Chrome","type":"context","displayName":"Chrome"},{"name":"Windows","type":"context","displayName":"Windows"},{"name":"Chrome, Windows","type":"context","displayName":"Chrome, Windows"}],"startTime":"2025-01-04T01:33:49.296742200+05:30[Asia/Colombo]","endTime":"2025-01-04T01:35:28.067522400+05:30[Asia/Colombo]","duration":32452,"projectKey":"","isManualTestingUpToDate":false,"context":"chrome,windows","dataTable":{"headers":["ExpenseType","Amount","Date","Note"],"rows":[{"values":["Planned Surgery","100","2025-02-01","Meal"],"lineNumber":33,"result":"SUCCESS"},{"values":["Transport","200","2024-01-02","Taxi"],"lineNumber":34,"result":"SUCCESS"},{"values":["Accommodation","300","2023-12-03","Hotel"],"lineNumber":35,"result":"SUCCESS"}],"predefinedRows":true,"scenarioOutline":"Given the user is directed to the View Claim page\n\rWhen the user clicks the Add Expenses button\n\rThen the add expenses modal should be displayed\n\rAnd the user selects the Expense Type \"\u003cExpenseType\u003e\"\n\rAnd the user enters the Amount \"\u003cAmount\u003e\"\n\rAnd the user enters the Date \"\u003cDate\u003e\"\n\rAnd the user enters the Note \"\u003cNote\u003e\"\n\rAnd the user clicks the save button\n\rThen the user should see the expense details Expense Type \"\u003cExpenseType\u003e\" and Amount \"\u003cAmount\u003e\" and Date \"\u003cDate\u003e\" and Note \"\u003cNote\u003e\"\n\rWhen the user clicks the Submit button\n\rThen the user should see the claim status as \"Submitted\"\n\r","dataSetDescriptors":[{"startRow":0,"rowCount":0,"name":"","description":""}]},"manual":false,"testSource":"Cucumber","result":"SUCCESS","scenarioOutline":"Given the user is directed to the View Claim page\r\nWhen the user clicks the Add Expenses button\r\nThen the add expenses modal should be displayed\r\nAnd the user selects the Expense Type \"\u003cExpenseType\u003e\"\r\nAnd the user enters the Amount \"\u003cAmount\u003e\"\r\nAnd the user enters the Date \"\u003cDate\u003e\"\r\nAnd the user enters the Note \"\u003cNote\u003e\"\r\nAnd the user clicks the save button\r\nThen the user should see the expense details Expense Type \"\u003cExpenseType\u003e\" and Amount \"\u003cAmount\u003e\" and Date \"\u003cDate\u003e\" and Note \"\u003cNote\u003e\"\r\nWhen the user clicks the Submit button\r\nThen the user should see the claim status as \"Submitted\""}